MANIFEST.in
README.rst
setup.py
addexampledata/__init__.py
addexampledata/models.py
addexampledata/management/__init__.py
addexampledata/management/commands/__init__.py
addexampledata/management/commands/addexampledata.py
addexampledata/management/commands/createexampleuser.py
django_addexampledata.egg-info/PKG-INFO
django_addexampledata.egg-info/SOURCES.txt
django_addexampledata.egg-info/dependency_links.txt
django_addexampledata.egg-info/not-zip-safe
django_addexampledata.egg-info/requires.txt
django_addexampledata.egg-info/top_level.txt