Metadata-Version: 1.0
Name: django-addexampledata
Version: 1.0
Summary: Easily bundle example data with your django apps.
Home-page: https://github.com/espenak/django_addexampledata
Author: Espen Angell Kristiansen
Author-email: UNKNOWN
License: BSD
Platform: UNKNOWN
Classifier: Development Status :: 5 - Production/Stable
Classifier: Environment :: Console
Classifier: Framework :: Django
Classifier: Intended Audience :: Developers
Classifier: License :: OSI Approved
Classifier: Operating System :: OS Independent
Classifier: Programming Language :: Python
